adafruit_bitmap_font/__init__.py
adafruit_bitmap_font/bdf.py
adafruit_bitmap_font/bitmap_font.py
adafruit_bitmap_font/glyph_cache.py
adafruit_bitmap_font/lvfontbin.py
adafruit_bitmap_font/pcf.py
adafruit_bitmap_font/ttf.py
adafruit_circuitpython_bitmap_font-2.3.3.dist-info/licenses/LICENSE
adafruit_circuitpython_bitmap_font-2.3.3.dist-info/METADATA
adafruit_circuitpython_bitmap_font-2.3.3.dist-info/WHEEL
adafruit_circuitpython_bitmap_font-2.3.3.dist-info/top_level.txt
adafruit_circuitpython_bitmap_font-2.3.3.dist-info/RECORD
